core_datetime/__init__.py
core_datetime/py.typed
core_datetime/utils.py
core_datetime-2.0.0.dist-info/licenses/LICENSE
core_datetime-2.0.0.dist-info/METADATA
core_datetime-2.0.0.dist-info/WHEEL
core_datetime-2.0.0.dist-info/top_level.txt
core_datetime-2.0.0.dist-info/RECORD
